{
    "js-practice-1": {
        "Valtteri Bottas": "1:18.410",
        "Lewis Hamilton": "1:18.749",
        "Max Verstappen": "1:19.191",
        "Charles Leclerc": "1:19.309",
        "Alexander Albon": "1:19.365",
        "Carlos Sainz": "1:19.441",
        "Sergio Perez": "1:19.907",
        "Kimi R\u00c3\u00a4ikk\u00c3\u00b6nen": "1:19.954",
        "Daniel Ricciardo": "1:20.058",
        "Pierre Gasly": "1:20.124",
        "Sebastian Vettel": "1:20.200",
        "Lando Norris": "1:20.207",
        "Daniil Kvyat": "1:20.278",
        "Kevin Magnussen": "1:20.846",
        "Lance Stroll": "1:20.954",
        "Antonio Giovinazzi": "1:21.009",
        "Romain Grosjean": "1:21.169",
        "George Russell": "1:21.374",
        "Esteban Ocon": "1:21.673",
        "Nicholas Latifi": "1:22.054"
    },
    "js-practice-2": {
        "Valtteri Bottas": "1:17.940",
        "Max Verstappen": "1:18.535",
        "Lando Norris": "1:18.743",
        "Charles Leclerc": "1:18.838",
        "Carlos Sainz": "1:19.113",
        "Sebastian Vettel": "1:19.175",
        "Pierre Gasly": "1:19.178",
        "Lewis Hamilton": "1:19.308",
        "Esteban Ocon": "1:19.496",
        "Alexander Albon": "1:19.643",
        "George Russell": "1:19.821",
        "Sergio Perez": "1:19.901",
        "Daniel Ricciardo": "1:19.987",
        "Nicholas Latifi": "1:20.465",
        "Kimi R\u00c3\u00a4ikk\u00c3\u00b6nen": "1:20.490",
        "Kevin Magnussen": "1:20.680",
        "Daniil Kvyat": "1:20.729",
        "Romain Grosjean": "1:20.867",
        "Lance Stroll": "1:20.983",
        "Antonio Giovinazzi": "1:21.396"
    },
    "js-practice-3": {
        "Valtteri Bottas": "1:16.654",
        "Lewis Hamilton": "1:16.680",
        "Max Verstappen": "1:16.812",
        "Pierre Gasly": "1:16.930",
        "Alexander Albon": "1:17.117",
        "Charles Leclerc": "1:17.229",
        "Carlos Sainz": "1:17.238",
        "Sergio Perez": "1:17.297",
        "Lando Norris": "1:17.478",
        "Esteban Ocon": "1:17.666",
        "Sebastian Vettel": "1:17.685",
        "Daniil Kvyat": "1:17.720",
        "Kimi R\u00c3\u00a4ikk\u00c3\u00b6nen": "1:17.922",
        "Daniel Ricciardo": "1:17.935",
        "George Russell": "1:18.032",
        "Lance Stroll": "1:18.100",
        "Antonio Giovinazzi": "1:18.201",
        "Kevin Magnussen": "1:18.287",
        "Nicholas Latifi": "1:18.397",
        "Romain Grosjean": "1:18.454"
    },
    "js-qualifying": {
        "Lewis Hamilton": "1:16.828",
        "Valtteri Bottas": "1:16.945",
        "Max Verstappen": "1:16.879",
        "Charles Leclerc": "1:17.421",
        "Sergio Perez": "1:17.370",
        "Alexander Albon": "1:17.435",
        "Carlos Sainz": "1:17.627",
        "Lando Norris": "1:17.547",
        "Pierre Gasly": "1:17.209",
        "Daniel Ricciardo": "1:17.621",
        "Esteban Ocon": "1:17.775",
        "Lance Stroll": "1:17.667",
        "Daniil Kvyat": "1:17.841",
        "George Russell": "1:17.931",
        "Sebastian Vettel": "1:17.446",
        "Kimi R\u00c3\u00a4ikk\u00c3\u00b6nen": "1:18.201",
        "Antonio Giovinazzi": "1:18.323",
        "Romain Grosjean": "1:18.364",
        "Kevin Magnussen": "1:18.508",
        "Nicholas Latifi": "1:18.777"
    },
    "placements": [
        "Lewis Hamilton",
        "Valtteri Bottas",
        "Max Verstappen",
        "Charles Leclerc",
        "Sergio Perez",
        "Alexander Albon",
        "Carlos Sainz",
        "Lando Norris",
        "Pierre Gasly",
        "Daniel Ricciardo",
        "Esteban Ocon",
        "Lance Stroll",
        "Daniil Kvyat",
        "George Russell",
        "Sebastian Vettel",
        "Kimi R\u00c3\u00a4ikk\u00c3\u00b6nen",
        "Antonio Giovinazzi",
        "Romain Grosjean",
        "Kevin Magnussen",
        "Nicholas Latifi"
    ],
    "track-name": "23 - 25 Oct 2020 (Portugal)"
}