{
    "js-practice-1": {
        "Lewis Hamilton": "1:29.033",
        "Valtteri Bottas": "1:29.482",
        "Sergio Perez": "1:30.000",
        "Carlos Sainz": "1:30.018",
        "Pierre Gasly": "1:30.049",
        "Max Verstappen": "1:30.294",
        "Alexander Albon": "1:30.302",
        "Esteban Ocon": "1:30.384",
        "Lance Stroll": "1:30.426",
        "Daniel Ricciardo": "1:30.508",
        "Charles Leclerc": "1:30.589",
        "Sebastian Vettel": "1:30.628",
        "Robert Kubica": "1:30.732",
        "Romain Grosjean": "1:30.832",
        "Kevin Magnussen": "1:30.854",
        "Antonio Giovinazzi": "1:30.896",
        "Daniil Kvyat": "1:31.020",
        "Lando Norris": "1:31.392",
        "Nicholas Latifi": "1:32.472",
        "Roy Nissany": "1:32.801"
    },
    "js-practice-2": {
        "Lewis Hamilton": "1:28.971",
        "Max Verstappen": "1:29.318",
        "Valtteri Bottas": "1:29.336",
        "Sergio Perez": "1:29.403",
        "Daniel Ricciardo": "1:29.462",
        "Pierre Gasly": "1:29.551",
        "Lando Norris": "1:29.841",
        "Lance Stroll": "1:29.871",
        "Daniil Kvyat": "1:29.900",
        "Alexander Albon": "1:30.014",
        "Esteban Ocon": "1:30.085",
        "Sebastian Vettel": "1:30.110",
        "Carlos Sainz": "1:30.271",
        "Charles Leclerc": "1:30.407",
        "Antonio Giovinazzi": "1:30.627",
        "Kevin Magnussen": "1:30.849",
        "Kimi R\u00c3\u00a4ikk\u00c3\u00b6nen": "1:30.928",
        "Nicholas Latifi": "1:30.973",
        "Romain Grosjean": "1:31.119",
        "George Russell": "1:31.636"
    },
    "js-practice-3": {
        "Max Verstappen": "1:28.355",
        "Lewis Hamilton": "1:28.618",
        "Valtteri Bottas": "1:28.721",
        "Alexander Albon": "1:29.018",
        "Carlos Sainz": "1:29.455",
        "Pierre Gasly": "1:29.472",
        "Lando Norris": "1:29.567",
        "Daniil Kvyat": "1:29.585",
        "Lance Stroll": "1:29.660",
        "Sergio Perez": "1:29.672",
        "Daniel Ricciardo": "1:29.684",
        "Esteban Ocon": "1:29.691",
        "Sebastian Vettel": "1:29.859",
        "Antonio Giovinazzi": "1:29.970",
        "Charles Leclerc": "1:30.183",
        "George Russell": "1:30.559",
        "Romain Grosjean": "1:30.652",
        "Kevin Magnussen": "1:30.759",
        "Kimi R\u00c3\u00a4ikk\u00c3\u00b6nen": "1:30.823",
        "Nicholas Latifi": "1:30.917"
    },
    "js-qualifying": {
        "Lewis Hamilton": "1:28.343",
        "Valtteri Bottas": "1:28.767",
        "Max Verstappen": "1:28.885",
        "Alexander Albon": "1:28.732",
        "Sergio Perez": "1:29.178",
        "Daniel Ricciardo": "1:29.005",
        "Esteban Ocon": "1:29.203",
        "Pierre Gasly": "1:28.971",
        "Lando Norris": "1:29.464",
        "Daniil Kvyat": "1:29.158",
        "Sebastian Vettel": "1:29.142",
        "Charles Leclerc": "1:29.137",
        "Lance Stroll": "1:28.679",
        "George Russell": "1:29.294",
        "Carlos Sainz": "1:28.975",
        "Antonio Giovinazzi": "1:29.491",
        "Kimi R\u00c3\u00a4ikk\u00c3\u00b6nen": "1:29.810",
        "Kevin Magnussen": "1:30.111",
        "Romain Grosjean": "1:30.138",
        "Nicholas Latifi": "1:30.182"
    },
    "placements": [
        "Lewis Hamilton",
        "Valtteri Bottas",
        "Max Verstappen",
        "Alexander Albon",
        "Sergio Perez",
        "Daniel Ricciardo",
        "Esteban Ocon",
        "Pierre Gasly",
        "Lando Norris",
        "Daniil Kvyat",
        "Sebastian Vettel",
        "Charles Leclerc",
        "Lance Stroll",
        "George Russell",
        "Carlos Sainz",
        "Antonio Giovinazzi",
        "Kimi R\u00c3\u00a4ikk\u00c3\u00b6nen",
        "Kevin Magnussen",
        "Romain Grosjean",
        "Nicholas Latifi"
    ],
    "track-name": "26 - 29 Nov 2020 (Bahrain)"
}